setup.py
objects/__init__.py
objects.egg-info/PKG-INFO
objects.egg-info/SOURCES.txt
objects.egg-info/dependency_links.txt
objects.egg-info/not-zip-safe
objects.egg-info/top_level.txt