Metadata-Version: 1.1
Name: objects
Version: 0.0.0
Summary: A corpus of object images
Home-page: http://github.com/Dallinger/Dallinger
Author: Jordan Suchow
Author-email: suchow@berkeley.edu
License: UNKNOWN
Keywords: objecs
Platform: UNKNOWN
Classifier: Development Status :: 4 - Beta
Classifier: Intended Audience :: Science/Research
Classifier: Topic :: Scientific/Engineering
Classifier: Programming Language :: Python :: 2.6
Classifier: Programming Language :: Python :: 2.7
